{
    "Features": [
        {
            "img": "assets/birla.png",
            "title": "Birla"
            },
        {
            "img": "assets/dr fixit.jpg",
            "title": "dr fixit"
            },
        {
            "img": "assets/myk.png",
            "title": "myk"
        },
        {
            "img": "assets/roff.png",
            "title": "roff"
        }
    ],
    "Header": {
    "title": "We are a Landing Page",
    "paragraph": "Lorem ipsum dolor sit amet, consectetur adipiscing elit. Duis sed dapibus leo nec ornare diam sed commodo nibh ante facilisis bibendum."
}
}
